pytechnote-0.2.0.dist-info/licenses/LICENSE
technote/__init__.py
technote/__main__.py
technote/cli.py
technote/config.py
technote/helpers.py
technote/models.py
technote/server.py
technote/services.py
technote/instance/notes.db
technote/static/favicon.svg
technote/static/main.js
technote/static/styles.css
technote/static/dist/.vite/manifest.json
technote/static/dist/assets/bootstrap-icons-BOrJxbIo.woff
technote/static/dist/assets/bootstrap-icons-BtvjY1KL.woff2
technote/static/dist/assets/main-ClYoXF_6.css
technote/static/dist/assets/main-DqoKvN0B.js
technote/static/examples_assets/decorator_pattern.jpg
technote/static/examples_assets/hash_table.png
technote/static/examples_assets/hash_table_array.png
technote/static/examples_assets/linked_list.png
technote/static/examples_assets/memory.png
technote/static/examples_assets/observer_pattern.jpg
technote/static/examples_assets/stack.png
technote/static/examples_assets/strategy_pattern.jpg
technote/static/examples_assets/tree.png
technote/static/examples_assets/tree_sequence.png
technote/static/examples_assets/trie.png
technote/static/examples_assets/trie_examples.png
technote/static/modules/editor.css
technote/static/modules/editor.js
technote/static/modules/searchbox.css
technote/static/modules/searchbox.js
technote/static/modules/sidebar.js
technote/static/modules/utils.js
technote/static/syntax-highlighting-themes/zenburn.css
technote/templates/about_modal.html
technote/templates/alert.html
technote/templates/document.html
technote/templates/home.html
technote/templates/layout.html
technote/templates/note.html
technote/templates/pandoc.html
technote/templates/shortcuts_modal.html
technote/templates/modules/editor.html
technote/templates/modules/searchbox.html
pytechnote-0.2.0.dist-info/METADATA
pytechnote-0.2.0.dist-info/WHEEL
pytechnote-0.2.0.dist-info/entry_points.txt
pytechnote-0.2.0.dist-info/top_level.txt
pytechnote-0.2.0.dist-info/RECORD
