Metadata-Version: 2.4
Name: pytechnote
Version: 0.2.0
License-File: LICENSE
Requires-Dist: Flask==3.0.3
Requires-Dist: pypandoc-binary==1.14
Dynamic: license-file
Dynamic: requires-dist
